ultimate_hosts_blacklist/central_repo_updater/__init__.py
ultimate_hosts_blacklist/central_repo_updater/clean.py
ultimate_hosts_blacklist/central_repo_updater/configuration.py
ultimate_hosts_blacklist/central_repo_updater/core.py
ultimate_hosts_blacklist/central_repo_updater/deploy.py
ultimate_hosts_blacklist/central_repo_updater/generate.py
ultimate_hosts_blacklist/central_repo_updater/repositories.py
ultimate_hosts_blacklist_central_repo_updater-1.11.0.dist-info/LICENSE
ultimate_hosts_blacklist_central_repo_updater-1.11.0.dist-info/METADATA
ultimate_hosts_blacklist_central_repo_updater-1.11.0.dist-info/WHEEL
ultimate_hosts_blacklist_central_repo_updater-1.11.0.dist-info/entry_points.txt
ultimate_hosts_blacklist_central_repo_updater-1.11.0.dist-info/top_level.txt
ultimate_hosts_blacklist_central_repo_updater-1.11.0.dist-info/RECORD
